morch
tests
