Metadata-Version: 2.1
Name: morch
Version: 1.0.3
Summary: SAGA Python Microservice Orchestrator
Home-page: https://github.com/hasanisaeed/morch
Author: Saeed Hasani Borzadaran
Author-email: hassanisaeed19@gmail.com
License: UNKNOWN
Project-URL: Bug Tracker, https://github.com/hasanisaeed/morch/issues/new
Keywords: microservice,saga,patterns,microservice patterns,saga pattern
Platform: UNKNOWN
Classifier: Programming Language :: Python :: 3
Classifier: License :: OSI Approved :: MIT License
Classifier: Operating System :: OS Independent
Requires-Python: >=3.9
License-File: LICENSE
